[
    {
        "UserID": 0,
        "username": "admin",
        "password": "123",
        "balance": 999,
        "ProfilePicture": "C:/Users/peter/Documents/Code/Python/Easter_project_mock/images/profilePic5.jpg"
    },
    {
        "UserID": 1,
        "username": "Max",
        "password": "maxiscool123",
        "balance": 43,
        "ProfilePicture": "C:/Users/peter/Documents/Code/Python/Easter_project_mock/images/profilePic1.jpg"
    },
    {
        "UserID": 2,
        "username": "Katie",
        "password": "qwerty",
        "balance": 580,
        "ProfilePicture": "C:/Users/peter/Documents/Code/Python/Easter_project_mock/images/profilePic5.jpg"
    },
    {
        "UserID": 3,
        "username": "Bob",
        "password": "12345b",
        "balance": 100,
        "ProfilePicture": "images/default.jpg"
    }
]